{
	"name": "pl_transform_product",
	"properties": {
		"activities": [
			{
				"name": "execute_transformation",
				"type": "DatabricksNotebook",
				"dependsOn": [],
				"policy": {
					"timeout": "0.12:00:00",
					"retry": 0,
					"retryIntervalInSeconds": 30,
					"secureOutput": false,
					"secureInput": false
				},
				"userProperties": [],
				"typeProperties": {
					"notebookPath": "/Shared/udemy/transform_product",
					"baseParameters": {
						"p_data": "20230626"
					}
				},
				"linkedServiceName": {
					"referenceName": "ls_databricks",
					"type": "LinkedServiceReference"
				}
			}
		],
		"annotations": [],
		"lastPublishTime": "2023-06-26T20:20:13Z"
	},
	"type": "Microsoft.DataFactory/factories/pipelines"
}