{
	"name": "ds_adls_binary",
	"properties": {
		"linkedServiceName": {
			"referenceName": "ls_adls",
			"type": "LinkedServiceReference"
		},
		"parameters": {
			"container": {
				"type": "string"
			},
			"folder": {
				"type": "string"
			}
		},
		"annotations": [],
		"type": "Binary",
		"typeProperties": {
			"location": {
				"type": "AzureBlobFSLocation",
				"folderPath": {
					"value": "@dataset().folder",
					"type": "Expression"
				},
				"fileSystem": {
					"value": "@dataset().container",
					"type": "Expression"
				}
			}
		}
	},
	"type": "Microsoft.DataFactory/factories/datasets"
}